pennylane_scaleway/__init__.py
pennylane_scaleway/aer_device.py
pennylane_scaleway/aqt_device.py
pennylane_scaleway/iqm_device.py
pennylane_scaleway/scw_device.py
pennylane_scaleway/utils.py
pennylane_scaleway-0.3.1.dist-info/licenses/LICENSE
pennylane_scaleway-0.3.1.dist-info/METADATA
pennylane_scaleway-0.3.1.dist-info/WHEEL
pennylane_scaleway-0.3.1.dist-info/entry_points.txt
pennylane_scaleway-0.3.1.dist-info/top_level.txt
pennylane_scaleway-0.3.1.dist-info/RECORD
