Metadata-Version: 2.4
Name: pennylane-scaleway
Version: 0.3.1
Summary: A Pennylane-compatible package to run pennylane circuits on Scaleway Quantum as a Service
Author: The Scaleway Developers
Author-email: vmacheret@scaleway.com
License: Apache 2
Project-URL: Documentation, https://www.scaleway.com/en/quantum-as-a-service/
Project-URL: Source, https://github.com/scaleway/pennylane-scaleway
Project-URL: Tracker, https://github.com/scaleway/pennylane-scaleway/issues
Requires-Python: >=3.12.0
License-File: LICENSE
Requires-Dist: coolname
Requires-Dist: pennylane
Requires-Dist: tenacity
Requires-Dist: qiskit-scaleway
Dynamic: author
Dynamic: author-email
Dynamic: description
Dynamic: description-content-type
Dynamic: license
Dynamic: license-file
Dynamic: project-url
Dynamic: requires-dist
Dynamic: requires-python
Dynamic: summary
